sqlitediff/Controller.py
sqlitediff/__init__.py
sqlitediff/__main__.py
sqlitediff/diff/DiffResult.py
sqlitediff/diff/SqliteDiff.py
sqlitediff/diff/__init__.py
sqlitediff/model/Snapshot.py
sqlitediff/model/Table.py
sqlitediff/model/TableResult.py
sqlitediff/model/__init__.py
sqlitediff/print/Printer.py
sqlitediff/print/__init__.py
sqlitediff/sqlite/Command.py
sqlitediff/sqlite/__init__.py
sqlitediff-1.0.0.dist-info/LICENSE.md
sqlitediff-1.0.0.dist-info/METADATA
sqlitediff-1.0.0.dist-info/WHEEL
sqlitediff-1.0.0.dist-info/entry_points.txt
sqlitediff-1.0.0.dist-info/top_level.txt
sqlitediff-1.0.0.dist-info/RECORD
