Metadata-Version: 2.1
Name: sqlitediff
Version: 1.0.0
Summary: Differential analysis of sqlite files
Home-page: https://github.com/5f0ne/sqlitediff
Author: 5f0
License: MIT
Classifier: Operating System :: OS Independent 
Classifier: Programming Language :: Python :: 3 
Classifier: License :: OSI Approved :: MIT License 
License-File: LICENSE.md
Requires-Dist: hash-calc
